[
    {
        "fees": -2500000000, 
        "ts": "1534534107", 
        "txid": "59f8ffbebedfee61c0ed8690a970f085453effc250fe3b9d162ea98c27b08be8", 
        "block": 1413956, 
        "in": [
            {
                "coinbase": "0344931504db21775b082601285f01000000052f6d70682f"
            }
        ], 
        "sent": 2500000000, 
        "out": [
            {
                "value": 0
            }, 
            {
                "addr": "MJpTHvn5TSgzr6mNsdEu28zMnQX232jr9q", 
                "value": 2500000000
            }
        ]
    }
]