[
    {
        "fees": -2500000000, 
        "ts": "1535133954", 
        "txid": "37ce268d87824e1fce725bbdfc126422d8bd6123e362aa9e1a987a2af6e1ef32", 
        "block": 1420295, 
        "in": [
            {
                "coinbase": "0307ac15040249805b0844018c3c01000000052f6d70682f"
            }
        ], 
        "sent": 2500000000, 
        "out": [
            {
                "value": 0
            }, 
            {
                "addr": "MJpTHvn5TSgzr6mNsdEu28zMnQX232jr9q", 
                "value": 2500000000
            }
        ]
    }
]