[
    {
        "fees": -2500000000, 
        "ts": "1535171441", 
        "txid": "2accf891c670650e5e7ef71a02cc7808f445a4fb5ceb0e5f59d14af5bab7f459", 
        "block": 1420686, 
        "in": [
            {
                "coinbase": "038ead150471db805b0824015b2000000000052f6d70682f"
            }
        ], 
        "sent": 2500000000, 
        "out": [
            {
                "value": 0
            }, 
            {
                "addr": "MJpTHvn5TSgzr6mNsdEu28zMnQX232jr9q", 
                "value": 2500000000
            }
        ]
    }
]