[
    {
        "fees": -2500000000, 
        "ts": "1535191887", 
        "txid": "f2d5899a5cd28d113e27311e05896fbdb2aefbf5612e32843b409b2a3b650b7a", 
        "block": 1420914, 
        "in": [
            {
                "coinbase": "0372ae15044f2b815b08440183e100000000052f6d70682f"
            }
        ], 
        "sent": 2500000000, 
        "out": [
            {
                "value": 0
            }, 
            {
                "addr": "MJpTHvn5TSgzr6mNsdEu28zMnQX232jr9q", 
                "value": 2500000000
            }
        ]
    }
]