[
    {
        "fees": -2500000000, 
        "ts": "1535202059", 
        "txid": "e2bb1635583d3e21b4409b3464fb44b0d2a5c611f2b0600a93e1cc0047c7a0ec", 
        "block": 1421020, 
        "in": [
            {
                "coinbase": "03dcae15040b53815b082001781c01000000052f6d70682f"
            }
        ], 
        "sent": 2500000000, 
        "out": [
            {
                "value": 0
            }, 
            {
                "addr": "MJpTHvn5TSgzr6mNsdEu28zMnQX232jr9q", 
                "value": 2500000000
            }
        ]
    }
]