[
    {
        "fees": -2500000000, 
        "ts": "1535373692", 
        "txid": "6de1ec0677fec256312d4a6aa1b19efc7e14bc88c63b39d7e0f393878065ebe7", 
        "block": 1422830, 
        "in": [
            {
                "coinbase": "03eeb515047cf1835b082601076601000000052f6d70682f"
            }
        ], 
        "sent": 2500000000, 
        "out": [
            {
                "value": 0
            }, 
            {
                "addr": "MJpTHvn5TSgzr6mNsdEu28zMnQX232jr9q", 
                "value": 2500000000
            }
        ]
    }
]