[
    {
        "fees": -2500000000, 
        "ts": "1535516004", 
        "txid": "d083a60b917dfffba6a4f123ae8b4dfb67bc8aea4e00c819e0e0a1ca2d744bcf", 
        "block": 1424333, 
        "in": [
            {
                "coinbase": "03cdbb1504641d865b084400e76d9e020004052f6d70682f"
            }
        ], 
        "sent": 2500000000, 
        "out": [
            {
                "value": 0
            }, 
            {
                "addr": "MJpTHvn5TSgzr6mNsdEu28zMnQX232jr9q", 
                "value": 2500000000
            }
        ]
    }
]