[
    {
        "ts": "1535634376",
        "in": [
            {
                "coinbase": "03b5c01504c8eb875b084401a10601000000052f6d70682f"
            }
        ],
        "block": 1425589,
        "sent": 2500000000,
        "txid": "a8c96103f8ed9f4b7c900600cbc31dd52055b01c388836d814cbfd592abc29ca",
        "fees": -2500000000,
        "out": [
            {
                "value": 0
            },
            {
                "addr": "MJpTHvn5TSgzr6mNsdEu28zMnQX232jr9q",
                "value": 2500000000
            }
        ]
    }
]