[
    {
        "ts": "1535674818",
        "in": [
            {
                "coinbase": "035ac21504c289885b082400b1f800000000052f6d70682f"
            }
        ],
        "block": 1426010,
        "sent": 2500000000,
        "txid": "d915c4323e19e8d1064e25b5fce282683be7952d7d2e97a5329c2914a6e7fe0c",
        "fees": -2500000000,
        "out": [
            {
                "value": 0
            },
            {
                "addr": "MJpTHvn5TSgzr6mNsdEu28zMnQX232jr9q",
                "value": 2500000000
            }
        ]
    }
]