[
    {
        "ts": "1536047265",
        "in": [
            {
                "coinbase": "03bcd11504a1388e5b085797bcb6000000000d2f6e6f64655374726174756d2f"
            }
        ],
        "block": 1429948,
        "sent": 2500000000,
        "txid": "69162879884430036b21f3de076c0af13a9ed3b83a01f9954f9ae1e4ea01009b",
        "fees": -2500000000,
        "out": [
            {
                "value": 0
            },
            {
                "addr": "M9YnFfBVUH2GqQeJKFmdkLskQTVRwbHPB7",
                "value": 2500000000
            },
            {
                "addr": "MB3gdWWt3oWQWtWMUufK626dUmT7pcFJLf",
                "value": 0
            }
        ]
    }
]